loris/__init__.py
loris/errors.py
loris/ignore.py
loris/io.py
loris/settings.py
loris/slack.py
loris/utils.py
loris/app/__init__.py
loris/app/app.py
loris/app/errors.py
loris/app/login.py
loris/app/pymysql_flask.py
loris/app/subprocess.py
loris/app/templates.py
loris/app/utils.py
loris/app/analysis/__init__.py
loris/app/analysis/run_populate.py
loris/app/autoscripting/__init__.py
loris/app/autoscripting/builder_forms.py
loris/app/autoscripting/config_reader.py
loris/app/autoscripting/form_creater.py
loris/app/autoscripting/run_insert_script.py
loris/app/autoscripting/utils.py
loris/app/forms/__init__.py
loris/app/forms/dynamic_field.py
loris/app/forms/dynamic_form.py
loris/app/forms/fixed.py
loris/app/forms/formmixin.py
loris/app/forms/wiki.py
loris/app/static/favicon.ico
loris/app/static/css/layout.main.css
loris/app/static/css/main.css
loris/app/static/css/main.quickfix.css
loris/app/static/css/main.responsive.css
loris/app/static/fonts/FontAwesome.otf
loris/app/static/fonts/fontawesome-webfont.eot
loris/app/static/fonts/fontawesome-webfont.svg
loris/app/static/fonts/fontawesome-webfont.ttf
loris/app/static/fonts/fontawesome-webfont.woff
loris/app/static/ico/apple-touch-icon-114-precomposed.png
loris/app/static/ico/apple-touch-icon-144-precomposed.png
loris/app/static/ico/apple-touch-icon-57-precomposed.png
loris/app/static/ico/apple-touch-icon-72-precomposed.png
loris/app/static/ico/favicon.png
loris/app/static/img/.gitkeep
loris/app/static/img/attention_loris.jpeg
loris/app/static/img/attention_loris.png
loris/app/static/img/home_loris.jpg
loris/app/static/img/loris.jpg
loris/app/static/img/loris.pdf
loris/app/static/img/loris.svg
loris/app/static/img/loris_icon.jpg
loris/app/static/img/loris_refresh.jpg
loris/app/static/img/slow_loris.jpg
loris/app/static/js/plugins.js
loris/app/static/js/script.js
loris/app/static/js/libs/bootstrap-3.1.1.min.js
loris/app/static/js/libs/modernizr-2.8.2.min.js
loris/app/static/js/libs/respond-1.4.2.min.js
lorisapp-0.1.8.dist-info/LICENSE
lorisapp-0.1.8.dist-info/METADATA
lorisapp-0.1.8.dist-info/WHEEL
lorisapp-0.1.8.dist-info/top_level.txt
lorisapp-0.1.8.dist-info/RECORD
